defy/PriceFinder.py
defy/Utilities.py
defy/Wallet.py
defy/__init__.py
defy/cli.py
defy/exchanges/Binance.py
defy/exchanges/BinanceFutures.py
defy/exchanges/__init__.py
defy/platforms/AutoFarm.py
defy/platforms/Fulcrum.py
defy/platforms/ValueDefi.py
defy/platforms/__init__.py
tests/MockContext.py
tests/__init__.py
tests/test_PriceFinder.py
tests/test_Utilities.py
tests/test_Wallet.py
tests/test_cli.py
tests/platforms/__init__.py
tests/platforms/test_AutoFarm.py
tests/platforms/test_Fulcrum.py
tests/platforms/test_ValueDefi.py
defy-0.4.0.dist-info/LICENSE
defy-0.4.0.dist-info/METADATA
defy-0.4.0.dist-info/WHEEL
defy-0.4.0.dist-info/entry_points.txt
defy-0.4.0.dist-info/top_level.txt
defy-0.4.0.dist-info/RECORD
