Metadata-Version: 2.1
Name: defy
Version: 0.4.0
Summary: A command line tool to lookup balance on blockchain network
Home-page: https://github.com/punparin/defy-cli
Author: Parin Kobboon
Author-email: punparin@gmail.com
License: UNKNOWN
Platform: UNKNOWN
Classifier: Programming Language :: Python :: 3
Classifier: License :: OSI Approved :: MIT License
Classifier: Operating System :: OS Independent
Requires-Python: >=3.6
Requires-Dist: click (==7.1.2)
Requires-Dist: configparser (==5.0.2)
Requires-Dist: requests (==2.25.1)
Requires-Dist: tabulate (==0.8.9)
Requires-Dist: web3 (==5.17.0)
Requires-Dist: python-binance (==0.7.9)
